alexa_reply/__init__.py
alexa_reply/ai.py
alexa_reply-0.1.2.dist-info/LICENSE
alexa_reply-0.1.2.dist-info/METADATA
alexa_reply-0.1.2.dist-info/WHEEL
alexa_reply-0.1.2.dist-info/top_level.txt
alexa_reply-0.1.2.dist-info/RECORD
