Metadata-Version: 2.1
Name: alexa-reply
Version: 0.1.2
Summary: An ai python package to respond to any message suitably
Home-page: https://github.com/The-mortal-phoenix/alexa-reply
Author: Phenoxis
Author-email: 1e1qwdqwe@gmail.com
License: MIT
Keywords: reply,ai,alexa,bot
Platform: UNKNOWN
Classifier: Intended Audience :: Developers
Classifier: License :: OSI Approved :: MIT License
Classifier: Programming Language :: Python :: 3
Requires-Dist: requests
